{
	"id" : "tesla",
	"name" : "Tesla",
	"description" : "Plugin pour monitorer une Tesla",
	"licence" : "AGPL",
	"icon" : "a fa-car",
	"author" : "vercors",
	"require" : "4.0",
	"category" : "devicecommunication",
	"display": "panel",
	"mobile": "panel",
	"hasDependency" : false,
	"hasOwnDeamon" : true,
	"maxDependancyInstallTime" : 0,
  "compatibility" : ["miniplus", "smart","rpi","docker","diy","mobile","v4","atlas"],
	"changelog" : "http://tesla.jeedom.free.fr/changelog",
	"changelog_beta" : "http://tesla.jeedom.free.fr/changelog",
	"documentation" : "http://tesla.jeedom.free.fr",
	"documentation_beta" : "http://tesla.jeedom.free.fr",
  "link": {
    "forum": "https://community.jeedom.com/tag/plugin-tesla"
  }
}
