{
	"id" : "sensibosky",
	"name" : "Sensibo Sky",
	"description" : "Plugin pour piloter le module Sensibo Sky",
	"licence" : "AGPL",
	"author" : "rombautsdidier",
	"require" : "3.0",
	"category" : "wellness",
	"hasDependency" : false,
	"hasOwnDeamon" : false,
	"maxDependancyInstallTime" : 0,
	"changelog" : "https://rombautsdidier.github.io/sensibosky/#language#/changelog",
	"documentation" : "https://rombautsdidier.github.io/sensibosky/#language#/",
	"link" : {
		"forum":"",
		"video" : ""
	},
	"language" : ["fr_FR","en_US"],
	"compatibility" : ["miniplus","smart","rpi","docker","diy","mobile"]
}
