{
	"id" : "mywallbox",
	"name" : "myWallBox",
	"pluginVersion": "1.3",  
	"description" : {
		"fr_FR": "Plugin pour la récupération des données d'une station de recharge WallBox."
	},
	"licence" : "GNU",
	"author" : "CStan77",
	"require" : "4.0.0",
	"category" : "energy",
	"hasDependency" : false,
	"hasOwnDeamon" : false,
	"maxDependancyInstallTime" : 0,
	"link" : {
		"forum": "https://community.jeedom.com/tag/plugin-mywallbox",
		"mon Jeddom": "https://community.jeedom.com/t/presentation-cstan77/72426"
	},
	"language" : ["fr_FR"],
	"compatibility" : ["jeedomboard","miniplus","smart","rpi","docker","diy","v4","atlas"],
	"changelog" : "https://github.com/CStan77/jeedom_doc/blob/main/myWallBox/changelog.md",
	"documentation" : "https://github.com/CStan77/jeedom_doc/blob/main/myWallBox/readme.md"
}